pdfminer/__init__.py
pdfminer/arcfour.py
pdfminer/ascii85.py
pdfminer/ccitt.py
pdfminer/cmapdb.py
pdfminer/converter.py
pdfminer/encodingdb.py
pdfminer/fontmetrics.py
pdfminer/glyphlist.py
pdfminer/high_level.py
pdfminer/image.py
pdfminer/latin_enc.py
pdfminer/layout.py
pdfminer/lzw.py
pdfminer/pdfcolor.py
pdfminer/pdfdevice.py
pdfminer/pdfdocument.py
pdfminer/pdffont.py
pdfminer/pdfinterp.py
pdfminer/pdfpage.py
pdfminer/pdfparser.py
pdfminer/pdftypes.py
pdfminer/psparser.py
pdfminer/rijndael.py
pdfminer/runlength.py
pdfminer/settings.py
pdfminer/utils.py
pdfminer2-20151206.data/scripts/dumppdf.py
pdfminer2-20151206.data/scripts/latin2ascii.py
pdfminer2-20151206.data/scripts/pdf2txt.py
pdfminer2-20151206.dist-info/DESCRIPTION.rst
pdfminer2-20151206.dist-info/METADATA
pdfminer2-20151206.dist-info/metadata.json
pdfminer2-20151206.dist-info/RECORD
pdfminer2-20151206.dist-info/top_level.txt
pdfminer2-20151206.dist-info/WHEEL
