Metadata-Version: 1.1
Name: pdfminer2
Version: 20151206
Summary: PDF parser and analyzer
Home-page: https://github.com/metachris/pdfminer
Author: Chris Hager
Author-email: chris@linuxuser.at
License: MIT
Keywords: pdf parser,pdf converter,layout analysis,text mining
Platform: UNKNOWN
Classifier: Programming Language :: Python
Classifier: Programming Language :: Python :: 2.7
Classifier: Programming Language :: Python :: 3.4
Classifier: Development Status :: 5 - Production/Stable
Classifier: Environment :: Console
Classifier: Intended Audience :: Developers
Classifier: Intended Audience :: Science/Research
Classifier: License :: OSI Approved :: MIT License
Classifier: Topic :: Text Processing
